dictflat/__init__.py
dictflat/dictflat.py
dictflat/dicttools.py
dictflat/tool_functions.py
dictflat-0.2.3.dist-info/METADATA
dictflat-0.2.3.dist-info/WHEEL
dictflat-0.2.3.dist-info/licenses/LICENSE
dictflat-0.2.3.dist-info/RECORD
