Metadata-Version: 2.4
Name: dictflat
Version: 0.2.3
Summary: A Python library to flatten a dictionary with nested dictionnaries and lists
License: MIT
License-File: LICENSE
Author: Arnaud Valmary
Requires-Python: >=3.10,<4.0
Classifier: License :: OSI Approved :: MIT License
Classifier: Programming Language :: Python :: 3
Classifier: Programming Language :: Python :: 3.10
Classifier: Programming Language :: Python :: 3.11
Classifier: Programming Language :: Python :: 3.12
Classifier: Programming Language :: Python :: 3.13
Classifier: Programming Language :: Python :: 3.14
Requires-Dist: py_overinspect (==0.1.0)
Project-URL: Repository, https://github.com/ArnaudValmary/py_dictflat
